vit_captioner/__init__.py
vit_captioner/cli.py
vit_captioner/version.py
vit_captioner/vit_captioner_video_example.py
vit_captioner/captioning/__init__.py
vit_captioner/captioning/image.py
vit_captioner/captioning/video.py
vit_captioner/keyframes/__init__.py
vit_captioner/keyframes/extractor.py
vit_captioner/keyframes/matcher.py
vit_captioner/utils/__init__.py
vit_captioner/utils/visualization.py
vit_captioner-0.1.2.dist-info/licenses/LICENSE
vit_captioner-0.1.2.dist-info/METADATA
vit_captioner-0.1.2.dist-info/WHEEL
vit_captioner-0.1.2.dist-info/entry_points.txt
vit_captioner-0.1.2.dist-info/top_level.txt
vit_captioner-0.1.2.dist-info/RECORD
