Metadata-Version: 2.4
Name: vit-captioner
Version: 0.1.2
Summary: A package for extracting keyframes from videos and generating captions using ViT-GPT2 model
Home-page: https://github.com/lachlanchen/VideoCaptionerWithVit
Author: Lachlan Chen
Author-email: lach@lazyingoronlyideas.art
Project-URL: Bug Reports, https://github.com/lachlanchen/VideoCaptionerWithVit/issues
Project-URL: Source, https://github.com/lachlanchen/VideoCaptionerWithVit
Keywords: video,captioning,ai,machine learning,ViT,GPT2,transformers
Classifier: Programming Language :: Python :: 3
Classifier: License :: OSI Approved :: MIT License
Classifier: Operating System :: OS Independent
Classifier: Development Status :: 4 - Beta
Classifier: Intended Audience :: Developers
Classifier: Intended Audience :: Science/Research
Classifier: Topic :: Multimedia :: Video
Classifier: Topic :: Scientific/Engineering :: Artificial Intelligence
Requires-Python: >=3.6
License-File: LICENSE
Requires-Dist: opencv-python
Requires-Dist: numpy
Requires-Dist: torch
Requires-Dist: transformers
Requires-Dist: Pillow
Requires-Dist: matplotlib
Requires-Dist: tqdm
Requires-Dist: Katna
Dynamic: author
Dynamic: author-email
Dynamic: classifier
Dynamic: description
Dynamic: description-content-type
Dynamic: home-page
Dynamic: keywords
Dynamic: license-file
Dynamic: project-url
Dynamic: requires-dist
Dynamic: requires-python
Dynamic: summary
